pc_tracker/__init__.py
pc_tracker/client.py
pc_tracker/logsys.py
pc_tracker-0.0.1.data/scripts/manage.py
scripts/__init__.py
scripts/manage.py
pc_tracker-0.0.1.dist-info/METADATA
pc_tracker-0.0.1.dist-info/WHEEL
pc_tracker-0.0.1.dist-info/top_level.txt
pc_tracker-0.0.1.dist-info/RECORD
