Metadata-Version: 2.1
Name: pc-tracker
Version: 0.0.1
Summary: Framework for tracking activity on PC
Home-page: https://github.com/DraganMatesic/pc_tracker
Author: Dragan Matesic
Author-email: dragan.matesic@gmail.com
License: MIT
Platform: UNKNOWN
Requires-Dist: pywin32
Requires-Dist: psutil
Requires-Dist: pynput
Requires-Dist: pysocks
